learn_kube/__init__.py
learn_kube/llm_service.py
learn_kube/main.py
learn_kube/models.py
learn_kube-0.1.0.dist-info/METADATA
learn_kube-0.1.0.dist-info/WHEEL
learn_kube-0.1.0.dist-info/RECORD
