Metadata-Version: 2.3
Name: learn-kube
Version: 0.1.0
Summary: 
Author: Reetu Raj Harsh
Author-email: reeturaj.harsh@neuralweb.tech
Requires-Python: >=3.11,<4.0
Classifier: Programming Language :: Python :: 3
Classifier: Programming Language :: Python :: 3.11
Classifier: Programming Language :: Python :: 3.12
Classifier: Programming Language :: Python :: 3.13
Requires-Dist: fastapi (>=0.115.12,<0.116.0)
Requires-Dist: google-genai (>=1.16.1,<2.0.0)
Requires-Dist: instructor (>=1.8.2,<2.0.0)
Requires-Dist: jsonref (>=1.1.0,<2.0.0)
Requires-Dist: python-dotenv (>=1.1.0,<2.0.0)
Requires-Dist: uvicorn (>=0.34.2,<0.35.0)
